LICENSE
MANIFEST.in
README.rst
janus.py
setup.py
janus_gateway.egg-info/PKG-INFO
janus_gateway.egg-info/SOURCES.txt
janus_gateway.egg-info/dependency_links.txt
janus_gateway.egg-info/requires.txt
janus_gateway.egg-info/top_level.txt
test/test_janus.py