Metadata-Version: 1.1
Name: janus-gateway
Version: 0.1.1
Summary: Python client for Janus.
Home-page: https://github.com/mayfieldrobotics/janus-py/
Author: Mayfield Robotics
Author-email: dev+janus-py@mayfieldrobotics.com
License: BSD
Platform: any
Classifier: Intended Audience :: Developers
Classifier: License :: OSI Approved :: BSD License
Classifier: Operating System :: OS Independent
Classifier: Programming Language :: Python
Classifier: Topic :: Software Development :: Libraries :: Python Modules
